{
  "updated": "2026-03-02T00:58:25.372829+04:00",
  "report_date": "2026-03-02",
  "total_sessions_7d": 77132,
  "total_sessions_prior": 153852,
  "wow_pct": -49.9,
  "top_pages": [
    {
      "topic": "2026",
      "title": "2026年 おすすめゼルダの伝説シリーズ",
      "category": "News",
      "sessions": 23036,
      "users": 22704,
      "pageviews": 23527,
      "bounce_rate": 0.631,
      "avg_duration": 24.1,
      "page_count": 11,
      "growth_pct": null,
      "urls": [
        "/ja/news/2026年におすすめのゼルダの伝説シリーズ/",
        "/ja/news/2026年におすすめのゼルダの伝説シリーズ/",
        "/ja/news/2026年におすすめのゼルダの伝説シリーズ/"
      ]
    },
    {
      "topic": "mario-tennis-fever",
      "title": "マリオテニスフィーバー：最強キャラtierリスト (Mario Tennis Fever)",
      "category": "Guide",
      "sessions": 11435,
      "users": 10891,
      "pageviews": 12178,
      "bounce_rate": 0.412,
      "avg_duration": 74.3,
      "page_count": 19,
      "growth_pct": -55.4,
      "urls": [
        "/ja/mario-tennis-fever/guides/マリオテニスフィーバー最強キャラtierリスト/",
        "/ja/mario-tennis-fever/guides/マリオテニスフィーバー最強キャラtierリスト/",
        "/ja/mario-tennis-fever/guides/mario-tennis-fever-初心者向け完全ガイド/"
      ]
    },
    {
      "topic": "nintendo-switch-online-2026",
      "title": "Nintendo Switch Online 2026年2月アップデート情報 | GAMES.GG",
      "category": "News",
      "sessions": 4941,
      "users": 4898,
      "pageviews": 5071,
      "bounce_rate": 0.679,
      "avg_duration": 18.2,
      "page_count": 1,
      "growth_pct": null,
      "urls": [
        "/ja/news/nintendo-switch-online-2026年2月アップデート情報/"
      ]
    },
    {
      "topic": "assassins-creed-codename-hexe",
      "title": "Assassin's Creed: Codename Hexe",
      "category": "Page",
      "sessions": 4489,
      "users": 4350,
      "pageviews": 4728,
      "bounce_rate": 0.551,
      "avg_duration": 46.2,
      "page_count": 9,
      "growth_pct": null,
      "urls": [
        "/assassins-creed-codename-hexe/",
        "/ko/assassins-creed-codename-hexe/",
        "/assassins-creed-codename-hexe/"
      ]
    },
    {
      "topic": "ポケモン30周年重大発表の可能性",
      "title": "ポケモン30周年、重大発表の可能性 (ポケモン30周年重大発表の可能性)",
      "category": "News",
      "sessions": 4159,
      "users": 3963,
      "pageviews": 4247,
      "bounce_rate": 0.461,
      "avg_duration": 61.0,
      "page_count": 4,
      "growth_pct": null,
      "urls": [
        "/ja/news/ポケモン30周年重大発表の可能性/",
        "/ja/news/ポケモン30周年重大発表の可能性/",
        "/ja/news/ポケモン30周年重大発表の可能性/"
      ]
    },
    {
      "topic": "/",
      "title": "GAM3S.GG | Gaming News, Reviews, Guides and Game Discovery",
      "category": "Page",
      "sessions": 3321,
      "users": 3089,
      "pageviews": 4369,
      "bounce_rate": 0.442,
      "avg_duration": 67.2,
      "page_count": 8,
      "growth_pct": -3.4,
      "urls": [
        "/",
        "/",
        "/"
      ]
    },
    {
      "topic": "slay-the-spire-2",
      "title": "Slay the Spire 2 早期アクセス開始日と協力プレイの詳細が明らかに | GAMES.GG",
      "category": "News",
      "sessions": 3292,
      "users": 3196,
      "pageviews": 3384,
      "bounce_rate": 0.637,
      "avg_duration": 35.7,
      "page_count": 7,
      "growth_pct": 794.6,
      "urls": [
        "/ja/news/slay-the-spire-2早期アクセス開始日と協力プレイの詳細が明らかに/",
        "/ja/news/slay-the-spire-2早期アクセス開始日と協力プレイの詳細が明らかに/",
        "/ja/news/slay-the-spire-2早期アクセス開始日と協力プレイの詳細が明らかに/"
      ]
    },
    {
      "topic": "pokémon-windとpokémon-waveのリーク情報",
      "title": "「Pokémon Wind」「Pokémon Wave」リーク情報 | GAMES.GG (Pokémon WindとPokémon Waveのリーク情報)",
      "category": "News",
      "sessions": 1844,
      "users": 1821,
      "pageviews": 1912,
      "bounce_rate": 0.533,
      "avg_duration": 27.9,
      "page_count": 2,
      "growth_pct": null,
      "urls": [
        "/ja/news/pokémon-windとpokémon-waveのリーク情報/",
        "/ja/news/pokémon-windとpokémon-waveのリーク情報/"
      ]
    },
    {
      "topic": "nintendo-mario-serisini-abd-ma",
      "title": "Nintendo Mario Serisini ABD Mağazalarına Getiriyor | GAMES.GG",
      "category": "News",
      "sessions": 1589,
      "users": 1555,
      "pageviews": 1763,
      "bounce_rate": 0.882,
      "avg_duration": 15.8,
      "page_count": 5,
      "growth_pct": null,
      "urls": [
        "/tr/news/nintendo-mario-serisini-abd-mağazalarına-getiriyor/",
        "/tr/news/nintendo-mario-serisini-abd-mağazalarına-getiriyor/",
        "/tr/news/nintendo-mario-serisini-abd-mağazalarına-getiriyor/"
      ]
    },
    {
      "topic": "xbox-series-x-volta-ao-estoque",
      "title": "Xbox Series X Volta ao Estoque Após Esgotar",
      "category": "News",
      "sessions": 1560,
      "users": 1516,
      "pageviews": 1603,
      "bounce_rate": 0.644,
      "avg_duration": 28.1,
      "page_count": 3,
      "growth_pct": 60.8,
      "urls": [
        "/pt-BR/news/xbox-series-x-volta-ao-estoque-após-esgotar/",
        "/pt-BR/news/xbox-series-x-volta-ao-estoque-após-esgotar/",
        "/pt-BR/news/xbox-series-x-volta-ao-estoque-após-esgotar/"
      ]
    }
  ],
  "top_guides": [
    {
      "topic": "mario-tennis-fever",
      "title": "マリオテニスフィーバー：最強キャラtierリスト (Mario Tennis Fever)",
      "category": "Guide",
      "sessions": 11435,
      "users": 10891,
      "pageviews": 12178,
      "bounce_rate": 0.412,
      "avg_duration": 74.3,
      "page_count": 19,
      "growth_pct": -55.4,
      "urls": [
        "/ja/mario-tennis-fever/guides/マリオテニスフィーバー最強キャラtierリスト/",
        "/ja/mario-tennis-fever/guides/マリオテニスフィーバー最強キャラtierリスト/",
        "/ja/mario-tennis-fever/guides/mario-tennis-fever-初心者向け完全ガイド/"
      ]
    },
    {
      "topic": "yapyap",
      "title": "YAPYAP 완드 & 주문 가이드: 모든 목록 | GAMES.GG",
      "category": "Guide",
      "sessions": 1146,
      "users": 773,
      "pageviews": 1207,
      "bounce_rate": 0.461,
      "avg_duration": 300.2,
      "page_count": 6,
      "growth_pct": 94.2,
      "urls": [
        "/ko/yapyap/guides/yapyap-완드-주문-가이드-모든-목록/",
        "/ko/yapyap/guides/yapyap-완드-주문-가이드-모든-목록/",
        "/ko/yapyap/guides/yapyap-완드-주문-가이드-모든-목록/"
      ]
    },
    {
      "topic": "steal-a-brainrot",
      "title": "Guía Steal A Brainrot: Evento San Valentín Pt 2",
      "category": "Guide",
      "sessions": 963,
      "users": 938,
      "pageviews": 1064,
      "bounce_rate": 0.857,
      "avg_duration": 18.0,
      "page_count": 3,
      "growth_pct": -94.4,
      "urls": [
        "/es/steal-a-brainrot/guides/guía-steal-a-brainrot-evento-san-valentín-pt-2/",
        "/es/steal-a-brainrot/guides/guía-steal-a-brainrot-evento-san-valentín-pt-2/",
        "/es/steal-a-brainrot/guides/guía-steal-a-brainrot-evento-san-valentín-pt-2/"
      ]
    },
    {
      "topic": "arc-raiders",
      "title": "Arc Raiders Surgeon Deckガイド：報酬と入手方法",
      "category": "Guide",
      "sessions": 803,
      "users": 776,
      "pageviews": 824,
      "bounce_rate": 0.587,
      "avg_duration": 49.3,
      "page_count": 4,
      "growth_pct": -69.5,
      "urls": [
        "/ja/arc-raiders/guides/arc-raiders-surgeon-deckガイド報酬と入手方法/",
        "/ja/arc-raiders/guides/arc-raiders-shrouded-skyアップデート知っておくべきこと全て/",
        "/ja/arc-raiders/guides/arc-raiders-shrouded-skyアップデート知っておくべきこと全て/"
      ]
    },
    {
      "topic": "poppy-playtime",
      "title": "Guía Poppy Playtime Cap. 5: Ubicaciones Cintas VHS",
      "category": "Guide",
      "sessions": 714,
      "users": 701,
      "pageviews": 813,
      "bounce_rate": 0.79,
      "avg_duration": 29.5,
      "page_count": 3,
      "growth_pct": -80.0,
      "urls": [
        "/es/poppy-playtime/guides/guía-poppy-playtime-cap-5-ubicaciones-de-las-3-cintas-vhs/",
        "/es/poppy-playtime/guides/guía-poppy-playtime-cap-5-ubicaciones-de-las-3-cintas-vhs/",
        "/es/poppy-playtime/guides/guía-poppy-playtime-cap-5-ubicaciones-de-las-3-cintas-vhs/"
      ]
    },
    {
      "topic": "marathon",
      "title": "Best Marathon Controller & Keyboard Settings | GAMES.GG",
      "category": "Guide",
      "sessions": 442,
      "users": 363,
      "pageviews": 450,
      "bounce_rate": 0.545,
      "avg_duration": 135.5,
      "page_count": 2,
      "growth_pct": null,
      "urls": [
        "/marathon/guides/marathon-best-controller-keyboard-settings/",
        "/marathon/guides/marathon-runner-shell-tier-list-best-picks-for-squad-play/"
      ]
    },
    {
      "topic": "overwatch-2",
      "title": "Overwatchガイド：アンランのランクプレイ向け最強のコツとテクニック (Overwatch 2)",
      "category": "Guide",
      "sessions": 228,
      "users": 218,
      "pageviews": 226,
      "bounce_rate": 0.627,
      "avg_duration": 77.9,
      "page_count": 1,
      "growth_pct": null,
      "urls": [
        "/ja/overwatch-2/guides/overwatchガイドアンランのランクプレイ向け最強のコツとテクニック/"
      ]
    }
  ],
  "top_news": [
    {
      "topic": "2026",
      "title": "2026年 おすすめゼルダの伝説シリーズ",
      "category": "News",
      "sessions": 23036,
      "users": 22704,
      "pageviews": 23527,
      "bounce_rate": 0.631,
      "avg_duration": 24.1,
      "page_count": 11,
      "growth_pct": null,
      "urls": [
        "/ja/news/2026年におすすめのゼルダの伝説シリーズ/",
        "/ja/news/2026年におすすめのゼルダの伝説シリーズ/",
        "/ja/news/2026年におすすめのゼルダの伝説シリーズ/"
      ]
    },
    {
      "topic": "nintendo-switch-online-2026",
      "title": "Nintendo Switch Online 2026年2月アップデート情報 | GAMES.GG",
      "category": "News",
      "sessions": 4941,
      "users": 4898,
      "pageviews": 5071,
      "bounce_rate": 0.679,
      "avg_duration": 18.2,
      "page_count": 1,
      "growth_pct": null,
      "urls": [
        "/ja/news/nintendo-switch-online-2026年2月アップデート情報/"
      ]
    },
    {
      "topic": "ポケモン30周年重大発表の可能性",
      "title": "ポケモン30周年、重大発表の可能性 (ポケモン30周年重大発表の可能性)",
      "category": "News",
      "sessions": 4159,
      "users": 3963,
      "pageviews": 4247,
      "bounce_rate": 0.461,
      "avg_duration": 61.0,
      "page_count": 4,
      "growth_pct": null,
      "urls": [
        "/ja/news/ポケモン30周年重大発表の可能性/",
        "/ja/news/ポケモン30周年重大発表の可能性/",
        "/ja/news/ポケモン30周年重大発表の可能性/"
      ]
    },
    {
      "topic": "slay-the-spire-2",
      "title": "Slay the Spire 2 早期アクセス開始日と協力プレイの詳細が明らかに | GAMES.GG",
      "category": "News",
      "sessions": 3292,
      "users": 3196,
      "pageviews": 3384,
      "bounce_rate": 0.637,
      "avg_duration": 35.7,
      "page_count": 7,
      "growth_pct": 794.6,
      "urls": [
        "/ja/news/slay-the-spire-2早期アクセス開始日と協力プレイの詳細が明らかに/",
        "/ja/news/slay-the-spire-2早期アクセス開始日と協力プレイの詳細が明らかに/",
        "/ja/news/slay-the-spire-2早期アクセス開始日と協力プレイの詳細が明らかに/"
      ]
    },
    {
      "topic": "pokémon-windとpokémon-waveのリーク情報",
      "title": "「Pokémon Wind」「Pokémon Wave」リーク情報 | GAMES.GG (Pokémon WindとPokémon Waveのリーク情報)",
      "category": "News",
      "sessions": 1844,
      "users": 1821,
      "pageviews": 1912,
      "bounce_rate": 0.533,
      "avg_duration": 27.9,
      "page_count": 2,
      "growth_pct": null,
      "urls": [
        "/ja/news/pokémon-windとpokémon-waveのリーク情報/",
        "/ja/news/pokémon-windとpokémon-waveのリーク情報/"
      ]
    },
    {
      "topic": "nintendo-mario-serisini-abd-ma",
      "title": "Nintendo Mario Serisini ABD Mağazalarına Getiriyor | GAMES.GG",
      "category": "News",
      "sessions": 1589,
      "users": 1555,
      "pageviews": 1763,
      "bounce_rate": 0.882,
      "avg_duration": 15.8,
      "page_count": 5,
      "growth_pct": null,
      "urls": [
        "/tr/news/nintendo-mario-serisini-abd-mağazalarına-getiriyor/",
        "/tr/news/nintendo-mario-serisini-abd-mağazalarına-getiriyor/",
        "/tr/news/nintendo-mario-serisini-abd-mağazalarına-getiriyor/"
      ]
    },
    {
      "topic": "xbox-series-x-volta-ao-estoque",
      "title": "Xbox Series X Volta ao Estoque Após Esgotar",
      "category": "News",
      "sessions": 1560,
      "users": 1516,
      "pageviews": 1603,
      "bounce_rate": 0.644,
      "avg_duration": 28.1,
      "page_count": 3,
      "growth_pct": 60.8,
      "urls": [
        "/pt-BR/news/xbox-series-x-volta-ao-estoque-após-esgotar/",
        "/pt-BR/news/xbox-series-x-volta-ao-estoque-após-esgotar/",
        "/pt-BR/news/xbox-series-x-volta-ao-estoque-após-esgotar/"
      ]
    },
    {
      "topic": "nieuwe-xbox-game-pass-games-februari",
      "title": "Nieuwe Xbox Game Pass Games Februari 2026",
      "category": "News",
      "sessions": 1294,
      "users": 1278,
      "pageviews": 1336,
      "bounce_rate": 0.663,
      "avg_duration": 24.2,
      "page_count": 3,
      "growth_pct": null,
      "urls": [
        "/nl/news/nieuwe-xbox-game-pass-games-februari-2026/",
        "/nl/news/nieuwe-xbox-game-pass-games-februari-2026/",
        "/nl/news/nieuwe-xbox-game-pass-games-februari-2026/"
      ]
    },
    {
      "topic": "epic-games-store",
      "title": "Epic Games StoreモバイルでResidualが無料に",
      "category": "News",
      "sessions": 986,
      "users": 958,
      "pageviews": 1048,
      "bounce_rate": 0.619,
      "avg_duration": 48.0,
      "page_count": 4,
      "growth_pct": -29.4,
      "urls": [
        "/ja/news/epic-games-storeモバイルでresidualが無料に/",
        "/ja/news/epic-games-storeモバイルでresidualが無料に/",
        "/ja/news/epic-games-storeモバイルでresidualが無料に/"
      ]
    },
    {
      "topic": "macbook-pro-m5-preço-reduzido-na",
      "title": "MacBook Pro M5: Preço Reduzido na Amazon (Macbook Pro M5 Preço Reduzido Na)",
      "category": "News",
      "sessions": 605,
      "users": 586,
      "pageviews": 621,
      "bounce_rate": 0.625,
      "avg_duration": 26.8,
      "page_count": 2,
      "growth_pct": -32.9,
      "urls": [
        "/pt-BR/news/macbook-pro-m5-preço-reduzido-na-amazon/",
        "/pt-BR/news/macbook-pro-m5-preço-reduzido-na-amazon/"
      ]
    },
    {
      "topic": "battlefield-6-season-2",
      "title": "Battlefield 6 Season 2: 主要な変更点と新要素",
      "category": "News",
      "sessions": 592,
      "users": 576,
      "pageviews": 598,
      "bounce_rate": 0.595,
      "avg_duration": 58.7,
      "page_count": 2,
      "growth_pct": null,
      "urls": [
        "/ja/news/battlefield-6-season-2-主要な変更点と新要素/",
        "/ja/news/battlefield-6-season-2-主要な変更点と新要素/"
      ]
    },
    {
      "topic": "novos-jogos-xbox-game-pass-fevereiro",
      "title": "Novos Jogos Xbox Game Pass Fevereiro 2026",
      "category": "News",
      "sessions": 586,
      "users": 572,
      "pageviews": 608,
      "bounce_rate": 0.643,
      "avg_duration": 35.4,
      "page_count": 2,
      "growth_pct": null,
      "urls": [
        "/pt-BR/news/novos-jogos-xbox-game-pass-fevereiro-2026/",
        "/pt-BR/news/novos-jogos-xbox-game-pass-fevereiro-2026/"
      ]
    },
    {
      "topic": "monitor-gamer-samsung-odyssey-oled-g5",
      "title": "Monitor Gamer Samsung Odyssey OLED G5 27″ por $350",
      "category": "News",
      "sessions": 578,
      "users": 563,
      "pageviews": 608,
      "bounce_rate": 0.555,
      "avg_duration": 35.3,
      "page_count": 2,
      "growth_pct": -34.8,
      "urls": [
        "/pt-BR/news/monitor-gamer-samsung-odyssey-oled-g5-27-por-350/",
        "/pt-BR/news/monitor-gamer-samsung-odyssey-oled-g5-27-por-350/"
      ]
    },
    {
      "topic": "xbox-elite-series-2-core-controller",
      "title": "Xbox Elite Series 2 Core Controller: Preço Reduzido",
      "category": "News",
      "sessions": 577,
      "users": 561,
      "pageviews": 606,
      "bounce_rate": 0.638,
      "avg_duration": 36.3,
      "page_count": 2,
      "growth_pct": null,
      "urls": [
        "/pt-BR/news/xbox-elite-series-2-core-controller-preço-reduzido/",
        "/pt-BR/news/xbox-elite-series-2-core-controller-preço-reduzido/"
      ]
    },
    {
      "topic": "kode-garden-horizons-roblox-februari-2026",
      "title": "Kode Garden Horizons Roblox Februari 2026",
      "category": "News",
      "sessions": 552,
      "users": 518,
      "pageviews": 589,
      "bounce_rate": 0.732,
      "avg_duration": 71.7,
      "page_count": 2,
      "growth_pct": null,
      "urls": [
        "/id/news/kode-garden-horizons-roblox-februari-2026/",
        "/id/news/kode-garden-horizons-roblox-februari-2026/"
      ]
    }
  ],
  "languages": [
    {
      "language": "Japanese",
      "sessions": 78529,
      "users": 74303,
      "pageviews": 86964,
      "growth_pct": -15.6
    },
    {
      "language": "English",
      "sessions": 64460,
      "users": 59021,
      "pageviews": 73064,
      "growth_pct": -50.4
    },
    {
      "language": "French",
      "sessions": 27630,
      "users": 24151,
      "pageviews": 31949,
      "growth_pct": -25.4
    },
    {
      "language": "Spanish",
      "sessions": 24281,
      "users": 21779,
      "pageviews": 27934,
      "growth_pct": -57.2
    },
    {
      "language": "Portuguese",
      "sessions": 17259,
      "users": 15769,
      "pageviews": 20040,
      "growth_pct": -55.2
    },
    {
      "language": "German",
      "sessions": 16396,
      "users": 14503,
      "pageviews": 18480,
      "growth_pct": -28.7
    },
    {
      "language": "Chinese",
      "sessions": 12867,
      "users": 11657,
      "pageviews": 15521,
      "growth_pct": -18.4
    },
    {
      "language": "Korean",
      "sessions": 12721,
      "users": 11494,
      "pageviews": 15322,
      "growth_pct": -4.2
    },
    {
      "language": "Russian",
      "sessions": 12315,
      "users": 10538,
      "pageviews": 15401,
      "growth_pct": -28.8
    },
    {
      "language": "Italian",
      "sessions": 8515,
      "users": 7708,
      "pageviews": 9705,
      "growth_pct": -33.9
    },
    {
      "language": "Turkish",
      "sessions": 8041,
      "users": 7560,
      "pageviews": 9429,
      "growth_pct": -59.7
    },
    {
      "language": "Dutch",
      "sessions": 4147,
      "users": 3910,
      "pageviews": 4540,
      "growth_pct": 33.5
    }
  ],
  "trending": [
    {
      "topic": "2026",
      "title": "2026年 おすすめゼルダの伝説シリーズ",
      "category": "News",
      "sessions": 23036,
      "users": 22704,
      "pageviews": 23527,
      "bounce_rate": 0.631,
      "avg_duration": 24.1,
      "page_count": 11,
      "growth_pct": null,
      "urls": [
        "/ja/news/2026年におすすめのゼルダの伝説シリーズ/",
        "/ja/news/2026年におすすめのゼルダの伝説シリーズ/",
        "/ja/news/2026年におすすめのゼルダの伝説シリーズ/"
      ]
    },
    {
      "topic": "nintendo-switch-online-2026",
      "title": "Nintendo Switch Online 2026年2月アップデート情報 | GAMES.GG",
      "category": "News",
      "sessions": 4941,
      "users": 4898,
      "pageviews": 5071,
      "bounce_rate": 0.679,
      "avg_duration": 18.2,
      "page_count": 1,
      "growth_pct": null,
      "urls": [
        "/ja/news/nintendo-switch-online-2026年2月アップデート情報/"
      ]
    },
    {
      "topic": "assassins-creed-codename-hexe",
      "title": "Assassin's Creed: Codename Hexe",
      "category": "Page",
      "sessions": 4489,
      "users": 4350,
      "pageviews": 4728,
      "bounce_rate": 0.551,
      "avg_duration": 46.2,
      "page_count": 9,
      "growth_pct": null,
      "urls": [
        "/assassins-creed-codename-hexe/",
        "/ko/assassins-creed-codename-hexe/",
        "/assassins-creed-codename-hexe/"
      ]
    },
    {
      "topic": "ポケモン30周年重大発表の可能性",
      "title": "ポケモン30周年、重大発表の可能性 (ポケモン30周年重大発表の可能性)",
      "category": "News",
      "sessions": 4159,
      "users": 3963,
      "pageviews": 4247,
      "bounce_rate": 0.461,
      "avg_duration": 61.0,
      "page_count": 4,
      "growth_pct": null,
      "urls": [
        "/ja/news/ポケモン30周年重大発表の可能性/",
        "/ja/news/ポケモン30周年重大発表の可能性/",
        "/ja/news/ポケモン30周年重大発表の可能性/"
      ]
    },
    {
      "topic": "slay-the-spire-2",
      "title": "Slay the Spire 2 早期アクセス開始日と協力プレイの詳細が明らかに | GAMES.GG",
      "category": "News",
      "sessions": 3292,
      "users": 3196,
      "pageviews": 3384,
      "bounce_rate": 0.637,
      "avg_duration": 35.7,
      "page_count": 7,
      "growth_pct": 794.6,
      "urls": [
        "/ja/news/slay-the-spire-2早期アクセス開始日と協力プレイの詳細が明らかに/",
        "/ja/news/slay-the-spire-2早期アクセス開始日と協力プレイの詳細が明らかに/",
        "/ja/news/slay-the-spire-2早期アクセス開始日と協力プレイの詳細が明らかに/"
      ]
    },
    {
      "topic": "pokémon-windとpokémon-waveのリーク情報",
      "title": "「Pokémon Wind」「Pokémon Wave」リーク情報 | GAMES.GG (Pokémon WindとPokémon Waveのリーク情報)",
      "category": "News",
      "sessions": 1844,
      "users": 1821,
      "pageviews": 1912,
      "bounce_rate": 0.533,
      "avg_duration": 27.9,
      "page_count": 2,
      "growth_pct": null,
      "urls": [
        "/ja/news/pokémon-windとpokémon-waveのリーク情報/",
        "/ja/news/pokémon-windとpokémon-waveのリーク情報/"
      ]
    },
    {
      "topic": "nintendo-mario-serisini-abd-ma",
      "title": "Nintendo Mario Serisini ABD Mağazalarına Getiriyor | GAMES.GG",
      "category": "News",
      "sessions": 1589,
      "users": 1555,
      "pageviews": 1763,
      "bounce_rate": 0.882,
      "avg_duration": 15.8,
      "page_count": 5,
      "growth_pct": null,
      "urls": [
        "/tr/news/nintendo-mario-serisini-abd-mağazalarına-getiriyor/",
        "/tr/news/nintendo-mario-serisini-abd-mağazalarına-getiriyor/",
        "/tr/news/nintendo-mario-serisini-abd-mağazalarına-getiriyor/"
      ]
    },
    {
      "topic": "xbox-series-x-volta-ao-estoque",
      "title": "Xbox Series X Volta ao Estoque Após Esgotar",
      "category": "News",
      "sessions": 1560,
      "users": 1516,
      "pageviews": 1603,
      "bounce_rate": 0.644,
      "avg_duration": 28.1,
      "page_count": 3,
      "growth_pct": 60.8,
      "urls": [
        "/pt-BR/news/xbox-series-x-volta-ao-estoque-após-esgotar/",
        "/pt-BR/news/xbox-series-x-volta-ao-estoque-após-esgotar/",
        "/pt-BR/news/xbox-series-x-volta-ao-estoque-após-esgotar/"
      ]
    }
  ],
  "fix_opportunities": [
    {
      "topic": "nintendo-mario-serisini-abd-ma",
      "title": "Nintendo Mario Serisini ABD Mağazalarına Getiriyor | GAMES.GG",
      "category": "News",
      "sessions": 1589,
      "users": 1555,
      "pageviews": 1763,
      "bounce_rate": 0.882,
      "avg_duration": 15.8,
      "page_count": 5,
      "growth_pct": null,
      "urls": [
        "/tr/news/nintendo-mario-serisini-abd-mağazalarına-getiriyor/",
        "/tr/news/nintendo-mario-serisini-abd-mağazalarına-getiriyor/",
        "/tr/news/nintendo-mario-serisini-abd-mağazalarına-getiriyor/"
      ]
    },
    {
      "topic": "steal-a-brainrot",
      "title": "Guía Steal A Brainrot: Evento San Valentín Pt 2",
      "category": "Guide",
      "sessions": 963,
      "users": 938,
      "pageviews": 1064,
      "bounce_rate": 0.857,
      "avg_duration": 18.0,
      "page_count": 3,
      "growth_pct": -94.4,
      "urls": [
        "/es/steal-a-brainrot/guides/guía-steal-a-brainrot-evento-san-valentín-pt-2/",
        "/es/steal-a-brainrot/guides/guía-steal-a-brainrot-evento-san-valentín-pt-2/",
        "/es/steal-a-brainrot/guides/guía-steal-a-brainrot-evento-san-valentín-pt-2/"
      ]
    }
  ],
  "gsc_top_queries": [
    {
      "query": "マリオテニス フィーバー 攻略",
      "clicks": 1575,
      "impressions": 4567,
      "ctr": 0.3449,
      "position": 1.7
    },
    {
      "query": "ポケモンデー",
      "clicks": 1372,
      "impressions": 14312,
      "ctr": 0.0959,
      "position": 2.4
    },
    {
      "query": "マリオテニスフィーバー 最強",
      "clicks": 919,
      "impressions": 1912,
      "ctr": 0.4806,
      "position": 1.3
    },
    {
      "query": "マリオ テニス フィーバー 最強 キャラ",
      "clicks": 740,
      "impressions": 1438,
      "ctr": 0.5146,
      "position": 1.1
    },
    {
      "query": "ポケモンデー 2026",
      "clicks": 612,
      "impressions": 5065,
      "ctr": 0.1208,
      "position": 1.8
    },
    {
      "query": "マリオテニス 最強キャラ",
      "clicks": 552,
      "impressions": 906,
      "ctr": 0.6093,
      "position": 1.5
    },
    {
      "query": "xbox game pass",
      "clicks": 535,
      "impressions": 11066,
      "ctr": 0.0483,
      "position": 3.3
    },
    {
      "query": "ポケモンプレゼンツ 2026",
      "clicks": 479,
      "impressions": 6893,
      "ctr": 0.0695,
      "position": 3.0
    },
    {
      "query": "nintendo switch online",
      "clicks": 430,
      "impressions": 1392,
      "ctr": 0.3089,
      "position": 4.2
    },
    {
      "query": "ポケモン ウィンド ウェーブ リーク",
      "clicks": 418,
      "impressions": 2563,
      "ctr": 0.1631,
      "position": 4.1
    }
  ],
  "gsc_rising_queries": [
    {
      "query": "ポケモンデー",
      "clicks": 1372,
      "impressions": 14312,
      "ctr": 0.0959,
      "position": 2.4,
      "growth_pct": null
    },
    {
      "query": "ポケモンデー 2026",
      "clicks": 612,
      "impressions": 5065,
      "ctr": 0.1208,
      "position": 1.8,
      "growth_pct": null
    },
    {
      "query": "xbox game pass",
      "clicks": 535,
      "impressions": 11066,
      "ctr": 0.0483,
      "position": 3.3,
      "growth_pct": 451.5
    },
    {
      "query": "ポケモンプレゼンツ 2026",
      "clicks": 479,
      "impressions": 6893,
      "ctr": 0.0695,
      "position": 3.0,
      "growth_pct": null
    },
    {
      "query": "nintendo switch online",
      "clicks": 430,
      "impressions": 1392,
      "ctr": 0.3089,
      "position": 4.2,
      "growth_pct": null
    },
    {
      "query": "ポケモン ウィンド ウェーブ リーク",
      "clicks": 418,
      "impressions": 2563,
      "ctr": 0.1631,
      "position": 4.1,
      "growth_pct": 770.8
    },
    {
      "query": "marathon server slam",
      "clicks": 382,
      "impressions": 6529,
      "ctr": 0.0585,
      "position": 1.7,
      "growth_pct": null
    },
    {
      "query": "assassin's creed: codename hexe",
      "clicks": 379,
      "impressions": 1354,
      "ctr": 0.2799,
      "position": 3.0,
      "growth_pct": null
    }
  ],
  "content_gaps": [
    {
      "query": "sailor piece codes",
      "impressions": 38616,
      "clicks": 88,
      "ctr": 0.0023,
      "position": 8.4
    },
    {
      "query": "resident evil requiem",
      "impressions": 38158,
      "clicks": 308,
      "ctr": 0.0081,
      "position": 4.1
    },
    {
      "query": "roblox",
      "impressions": 27765,
      "clicks": 21,
      "ctr": 0.0008,
      "position": 4.2
    },
    {
      "query": "xbox",
      "impressions": 27718,
      "clicks": 91,
      "ctr": 0.0033,
      "position": 3.0
    },
    {
      "query": "spin a baddie codes",
      "impressions": 20711,
      "clicks": 35,
      "ctr": 0.0017,
      "position": 7.7
    }
  ],
  "page2_wins": [
    {
      "query": "steal a brainrot script",
      "impressions": 715,
      "clicks": 42,
      "position": 12.3
    },
    {
      "query": "buckshot roulette",
      "impressions": 376,
      "clicks": 28,
      "position": 11.4
    },
    {
      "query": "clover pit unblocked",
      "impressions": 80,
      "clicks": 34,
      "position": 14.7
    },
    {
      "query": "cloverpit unblocked",
      "impressions": 67,
      "clicks": 25,
      "position": 15.3
    }
  ],
  "low_ctr_pages": [
    {
      "name": "Sailor Piece Roblox Codes February 2026",
      "impressions": 69314,
      "clicks": 141,
      "ctr": 0.002,
      "position": 8.5
    },
    {
      "name": "Mewgenics All Quests And How To Complete Them",
      "impressions": 38937,
      "clicks": 487,
      "ctr": 0.0125,
      "position": 7.7
    },
    {
      "name": "Sailor Piece Roblox Codes February 2026",
      "impressions": 19554,
      "clicks": 230,
      "ctr": 0.0118,
      "position": 4.9
    },
    {
      "name": "Códigos Roblox Anime Ghosts Fevereiro 2026",
      "impressions": 19330,
      "clicks": 125,
      "ctr": 0.0065,
      "position": 6.0
    },
    {
      "name": "Révélations Majeures Attendues Pour Le 30E Anniversaire De Pokémon",
      "impressions": 17644,
      "clicks": 298,
      "ctr": 0.0169,
      "position": 3.4
    }
  ],
  "easy_wins": {
    "cover_now": [
      {
        "game": "Counter-Strike 2",
        "hype_score": 752.6,
        "sources": [
          "Steam Rising"
        ],
        "twitch_viewers": 0,
        "steam_players": 1293667
      },
      {
        "game": "League of Legends",
        "hype_score": 565.2,
        "sources": [
          "Twitch #1"
        ],
        "twitch_viewers": 565241,
        "steam_players": 0
      },
      {
        "game": "RESIDENT EVIL: requiem",
        "hype_score": 482.1,
        "sources": [
          "Twitch #2",
          "Steam Trending #1",
          "Steam Rising"
        ],
        "twitch_viewers": 171426,
        "steam_players": 269784
      },
      {
        "game": "VALORANT",
        "hype_score": 220.2,
        "sources": [
          "Twitch #3"
        ],
        "twitch_viewers": 220233,
        "steam_players": 0
      },
      {
        "game": "Counter-Strike",
        "hype_score": 169.3,
        "sources": [
          "Twitch #4"
        ],
        "twitch_viewers": 169291,
        "steam_players": 0
      },
      {
        "game": "Baldur's Gate 3",
        "hype_score": 136.3,
        "sources": [
          "Steam Trending #3",
          "Steam Rising"
        ],
        "twitch_viewers": 0,
        "steam_players": 85060
      },
      {
        "game": "Apex Legends",
        "hype_score": 117.8,
        "sources": [
          "Breakout #9",
          "Steam Trending #10",
          "Steam Rising"
        ],
        "twitch_viewers": 9668,
        "steam_players": 71969
      },
      {
        "game": "HELLDIVERS™ 2",
        "hype_score": 115.9,
        "sources": [
          "Steam Trending #4",
          "Steam Rising"
        ],
        "twitch_viewers": 0,
        "steam_players": 81215
      },
      {
        "game": "Marvel Rivals",
        "hype_score": 108.0,
        "sources": [
          "Breakout #8",
          "Steam Trending #6"
        ],
        "twitch_viewers": 9765,
        "steam_players": 93344
      },
      {
        "game": "EA Sports FC 26",
        "hype_score": 82.5,
        "sources": [
          "Twitch #6"
        ],
        "twitch_viewers": 82509,
        "steam_players": 0
      }
    ],
    "capitalize": [
      {
        "game": "ARC Raiders",
        "hype_score": 393.5,
        "gam3s_sessions": 803,
        "gam3s_title": "Arc Raiders Surgeon Deckガイド：報酬と入手方法",
        "growth_pct": -69.5
      },
      {
        "game": "Slay the Spire 2",
        "hype_score": 7,
        "gam3s_sessions": 3292,
        "gam3s_title": "Slay the Spire 2 早期アクセス開始日と協力プレイの詳細が明らかに | GAMES.GG",
        "growth_pct": 794.6
      }
    ],
    "update_needed": []
  }
}